{
  "docs": [
    {
      "modelType": "user",
      "name": "Roberta Banes",
      "stars": 88,
      "range": "starter"
    },
    {
      "modelType": "user",
      "name": "Clementina Havens",
      "stars": 53,
      "range": "starter"
    },
    {
      "modelType": "user",
      "name": "Angel Villagran",
      "stars": 62,
      "range": "starter"
    },
    {
      "modelType": "user",
      "name": "Tomasa Ledoux",
      "stars": 32,
      "range": "starter"
    },
    {
      "modelType": "user",
      "name": "Louanne Magdaleno",
      "stars": 37,
      "range": "starter"
    },
    {
      "modelType": "user",
      "name": "Cecila Browne",
      "stars": 8,
      "range": "starter"
    },
    {
      "modelType": "user",
      "name": "Cornelia Rosales",
      "stars": 82,
      "range": "starter"
    },
    {
      "modelType": "user",
      "name": "Mickie Alsobrook",
      "stars": 34,
      "range": "starter"
    },
    {
      "modelType": "user",
      "name": "Shara Elsworth",
      "stars": 68,
      "range": "starter"
    },
    {
      "modelType": "user",
      "name": "Sheri Szewczyk",
      "stars": 68,
      "range": "starter"
    },
    {
      "modelType": "user",
      "name": "Bonita Waldeck",
      "stars": 61,
      "range": "starter"
    },
    {
      "modelType": "user",
      "name": "Jeanette Lesperance",
      "stars": 82,
      "range": "starter"
    },
    {
      "modelType": "user",
      "name": "Karey Hofmeister",
      "stars": 38,
      "range": "starter"
    },
    {
      "modelType": "user",
      "name": "Carlie Fondren",
      "stars": 85,
      "range": "starter"
    },
    {
      "modelType": "user",
      "name": "Nichelle Partlow",
      "stars": 28,
      "range": "starter"
    },
    {
      "modelType": "user",
      "name": "Donn Lizarraga",
      "stars": 15,
      "range": "starter"
    },
    {
      "modelType": "user",
      "name": "Karine Cacciatore",
      "stars": 7,
      "range": "starter"
    },
    {
      "modelType": "user",
      "name": "Lavonna Caballero",
      "stars": 59,
      "range": "starter"
    },
    {
      "modelType": "user",
      "name": "Eveline Sifford",
      "stars": 13,
      "range": "starter"
    },
    {
      "modelType": "user",
      "name": "Eliza Miyamoto",
      "stars": 32,
      "range": "starter"
    },
    {
      "modelType": "user",
      "name": "Lakendra Towery",
      "stars": 53,
      "range": "starter"
    },
    {
      "modelType": "user",
      "name": "Arnette Bridger",
      "stars": 17,
      "range": "starter"
    },
    {
      "modelType": "user",
      "name": "Luba Eichhorn",
      "stars": 91,
      "range": "starter"
    },
    {
      "modelType": "user",
      "name": "Chae Jackson",
      "stars": 33,
      "range": "starter"
    },
    {
      "modelType": "user",
      "name": "Nereida Lomeli",
      "stars": 65,
      "range": "starter"
    },
    {
      "modelType": "user",
      "name": "Setsuko Yung",
      "stars": 50,
      "range": "starter"
    },
    {
      "modelType": "user",
      "name": "Tanna Sauders",
      "stars": 1,
      "range": "starter"
    },
    {
      "modelType": "user",
      "name": "Karl Romano",
      "stars": 32,
      "range": "starter"
    },
    {
      "modelType": "user",
      "name": "Kali Burgener",
      "stars": 70,
      "range": "starter"
    },
    {
      "modelType": "user",
      "name": "Miguel Hamed",
      "stars": 2,
      "range": "starter"
    },
    {
      "modelType": "user",
      "name": "Joette Roemer",
      "stars": 3,
      "range": "starter"
    },
    {
      "modelType": "user",
      "name": "Peggy Sandstrom",
      "stars": 45,
      "range": "starter"
    },
    {
      "modelType": "user",
      "name": "Candis Drescher",
      "stars": 9,
      "range": "starter"
    },
    {
      "modelType": "user",
      "name": "Wei Blakes",
      "stars": 71,
      "range": "starter"
    },
    {
      "modelType": "user",
      "name": "Eddy Jeanpierre",
      "stars": 90,
      "range": "starter"
    },
    {
      "modelType": "user",
      "name": "Carli Albritton",
      "stars": 78,
      "range": "starter"
    },
    {
      "modelType": "user",
      "name": "Mozella Dillenbeck",
      "stars": 40,
      "range": "starter"
    },
    {
      "modelType": "user",
      "name": "Corina Willson",
      "stars": 22,
      "range": "starter"
    },
    {
      "modelType": "user",
      "name": "Harrison Mcalexander",
      "stars": 89,
      "range": "starter"
    },
    {
      "modelType": "user",
      "name": "Jonathan Bang",
      "stars": 22,
      "range": "starter"
    },
    {
      "modelType": "user",
      "name": "Jaymie Sallee",
      "stars": 1,
      "range": "starter"
    },
    {
      "modelType": "user",
      "name": "Madge Walter",
      "stars": 35,
      "range": "starter"
    },
    {
      "modelType": "user",
      "name": "Corrina Justiniano",
      "stars": 1,
      "range": "starter"
    },
    {
      "modelType": "user",
      "name": "Odelia Coburn",
      "stars": 16,
      "range": "starter"
    },
    {
      "modelType": "user",
      "name": "Tracee Cupp",
      "stars": 5,
      "range": "starter"
    },
    {
      "modelType": "user",
      "name": "Tania Buffum",
      "stars": 46,
      "range": "starter"
    },
    {
      "modelType": "user",
      "name": "Ouida Melo",
      "stars": 36,
      "range": "starter"
    },
    {
      "modelType": "user",
      "name": "Tonia Bryon",
      "stars": 14,
      "range": "starter"
    },
    {
      "modelType": "user",
      "name": "Dorris Bouffard",
      "stars": 62,
      "range": "starter"
    },
    {
      "modelType": "user",
      "name": "Karina Okane",
      "stars": 57,
      "range": "starter"
    },
    {
      "modelType": "user",
      "name": "Livia Truesdale",
      "stars": 5,
      "range": "starter"
    },
    {
      "modelType": "user",
      "name": "Dominic Henrich",
      "stars": 12,
      "range": "starter"
    },
    {
      "modelType": "user",
      "name": "Katia Furlough",
      "stars": 33,
      "range": "starter"
    },
    {
      "modelType": "user",
      "name": "Flossie Ahmad",
      "stars": 53,
      "range": "starter"
    },
    {
      "modelType": "user",
      "name": "Bruna Sussman",
      "stars": 52,
      "range": "starter"
    },
    {
      "modelType": "user",
      "name": "Hanna Sykes",
      "stars": 80,
      "range": "starter"
    },
    {
      "modelType": "user",
      "name": "Penney Imburgia",
      "stars": 86,
      "range": "starter"
    },
    {
      "modelType": "user",
      "name": "Nancee Dieguez",
      "stars": 69,
      "range": "starter"
    },
    {
      "modelType": "user",
      "name": "Lola Cofer",
      "stars": 8,
      "range": "starter"
    },
    {
      "modelType": "user",
      "name": "Torri Aburto",
      "stars": 57,
      "range": "starter"
    },
    {
      "modelType": "user",
      "name": "Na Barnhouse",
      "stars": 81,
      "range": "starter"
    },
    {
      "modelType": "user",
      "name": "Sandie Bilal",
      "stars": 11,
      "range": "starter"
    },
    {
      "modelType": "user",
      "name": "Caryl Shrader",
      "stars": 98,
      "range": "starter"
    },
    {
      "modelType": "user",
      "name": "Benton Rosol",
      "stars": 78,
      "range": "starter"
    },
    {
      "modelType": "user",
      "name": "Towanda Veatch",
      "stars": 44,
      "range": "starter"
    },
    {
      "modelType": "user",
      "name": "Abdul Jacobs",
      "stars": 16,
      "range": "starter"
    },
    {
      "modelType": "user",
      "name": "Bethann Marin",
      "stars": 37,
      "range": "starter"
    },
    {
      "modelType": "user",
      "name": "Freddy Hodge",
      "stars": 76,
      "range": "starter"
    },
    {
      "modelType": "user",
      "name": "Lidia Rowe",
      "stars": 6,
      "range": "starter"
    },
    {
      "modelType": "user",
      "name": "Joella Heffley",
      "stars": 80,
      "range": "starter"
    },
    {
      "modelType": "user",
      "name": "Denisse Derosa",
      "stars": 88,
      "range": "starter"
    },
    {
      "modelType": "user",
      "name": "Yetta Gathers",
      "stars": 99,
      "range": "starter"
    },
    {
      "modelType": "user",
      "name": "Hermina Sater",
      "stars": 69,
      "range": "starter"
    },
    {
      "modelType": "user",
      "name": "Aron Tillman",
      "stars": 96,
      "range": "starter"
    },
    {
      "modelType": "user",
      "name": "Anna Shock",
      "stars": 85,
      "range": "starter"
    },
    {
      "modelType": "user",
      "name": "Tam Causey",
      "stars": 65,
      "range": "starter"
    },
    {
      "modelType": "user",
      "name": "Cayla Rothchild",
      "stars": 24,
      "range": "starter"
    },
    {
      "modelType": "user",
      "name": "Fannie Vosburgh",
      "stars": 47,
      "range": "starter"
    },
    {
      "modelType": "user",
      "name": "Wei Hone",
      "stars": 45,
      "range": "starter"
    },
    {
      "modelType": "user",
      "name": "Patricia Prosperie",
      "stars": 5,
      "range": "starter"
    },
    {
      "modelType": "user",
      "name": "Juliann Gravatt",
      "stars": 3,
      "range": "starter"
    },
    {
      "modelType": "user",
      "name": "Manual Aho",
      "stars": 44,
      "range": "starter"
    },
    {
      "modelType": "user",
      "name": "Rocio Dantonio",
      "stars": 14,
      "range": "starter"
    },
    {
      "modelType": "user",
      "name": "Alyson Warshaw",
      "stars": 70,
      "range": "starter"
    },
    {
      "modelType": "user",
      "name": "Phillis Musil",
      "stars": 78,
      "range": "starter"
    },
    {
      "modelType": "user",
      "name": "Teresia Fukushima",
      "stars": 75,
      "range": "starter"
    },
    {
      "modelType": "user",
      "name": "Romona Bottoms",
      "stars": 69,
      "range": "starter"
    },
    {
      "modelType": "user",
      "name": "Birgit Whitmarsh",
      "stars": 99,
      "range": "starter"
    },
    {
      "modelType": "user",
      "name": "Melodie Bradford",
      "stars": 79,
      "range": "starter"
    },
    {
      "modelType": "user",
      "name": "Johna Seip",
      "stars": 95,
      "range": "starter"
    },
    {
      "modelType": "user",
      "name": "Evelyn Onan",
      "stars": 86,
      "range": "starter"
    },
    {
      "modelType": "user",
      "name": "Heather Muniz",
      "stars": 45,
      "range": "starter"
    },
    {
      "modelType": "user",
      "name": "Taren Spaeth",
      "stars": 83,
      "range": "starter"
    },
    {
      "modelType": "user",
      "name": "Genia Hanlin",
      "stars": 99,
      "range": "starter"
    },
    {
      "modelType": "user",
      "name": "Orlando Barna",
      "stars": 11,
      "range": "starter"
    },
    {
      "modelType": "user",
      "name": "Elfreda Dawley",
      "stars": 77,
      "range": "starter"
    },
    {
      "modelType": "user",
      "name": "Gertie Sommerfeld",
      "stars": 78,
      "range": "starter"
    },
    {
      "modelType": "user",
      "name": "Caroyln Goldsby",
      "stars": 72,
      "range": "starter"
    },
    {
      "modelType": "user",
      "name": "Jocelyn Greggs",
      "stars": 84,
      "range": "starter"
    },
    {
      "modelType": "user",
      "name": "Saturnina Large",
      "stars": 54,
      "range": "starter"
    },
    {
      "modelType": "user",
      "name": "Kristel Unger",
      "stars": 2,
      "range": "starter"
    },
    {
      "modelType": "user",
      "name": "Florance Linck",
      "stars": 33,
      "range": "starter"
    },
    {
      "modelType": "user",
      "name": "Dwight Pelto",
      "stars": 29,
      "range": "starter"
    },
    {
      "modelType": "user",
      "name": "Judy Funaro",
      "stars": 78,
      "range": "starter"
    },
    {
      "modelType": "user",
      "name": "Lucia Mahi",
      "stars": 54,
      "range": "starter"
    },
    {
      "modelType": "user",
      "name": "Ai Mcmorris",
      "stars": 63,
      "range": "starter"
    },
    {
      "modelType": "user",
      "name": "Asuncion Niehaus",
      "stars": 88,
      "range": "starter"
    },
    {
      "modelType": "user",
      "name": "Ed Shoaff",
      "stars": 85,
      "range": "starter"
    },
    {
      "modelType": "user",
      "name": "Charlsie Hodak",
      "stars": 38,
      "range": "starter"
    },
    {
      "modelType": "user",
      "name": "Nella Bingham",
      "stars": 57,
      "range": "starter"
    },
    {
      "modelType": "user",
      "name": "Lorelei Rolling",
      "stars": 59,
      "range": "starter"
    },
    {
      "modelType": "user",
      "name": "Deena Bever",
      "stars": 69,
      "range": "starter"
    },
    {
      "modelType": "user",
      "name": "Debora Laster",
      "stars": 5,
      "range": "starter"
    },
    {
      "modelType": "user",
      "name": "Shane Anwar",
      "stars": 44,
      "range": "starter"
    },
    {
      "modelType": "user",
      "name": "Danuta Knarr",
      "stars": 81,
      "range": "starter"
    },
    {
      "modelType": "user",
      "name": "Elisabeth Abbey",
      "stars": 41,
      "range": "starter"
    },
    {
      "modelType": "user",
      "name": "Laurette Kruger",
      "stars": 31,
      "range": "starter"
    },
    {
      "modelType": "user",
      "name": "Viviana Ressler",
      "stars": 60,
      "range": "starter"
    },
    {
      "modelType": "user",
      "name": "Florentino Moise",
      "stars": 41,
      "range": "starter"
    },
    {
      "modelType": "user",
      "name": "Hettie Monreal",
      "stars": 36,
      "range": "starter"
    },
    {
      "modelType": "user",
      "name": "Roni Masiello",
      "stars": 62,
      "range": "starter"
    },
    {
      "modelType": "user",
      "name": "Camille Greenland",
      "stars": 62,
      "range": "starter"
    },
    {
      "modelType": "user",
      "name": "Ivette Hernadez",
      "stars": 24,
      "range": "starter"
    },
    {
      "modelType": "user",
      "name": "Natacha Mcbrayer",
      "stars": 45,
      "range": "starter"
    },
    {
      "modelType": "user",
      "name": "Madalyn Richie",
      "stars": 17,
      "range": "starter"
    },
    {
      "modelType": "user",
      "name": "Mario Celaya",
      "stars": 19,
      "range": "starter"
    },
    {
      "modelType": "user",
      "name": "Lina Twilley",
      "stars": 54,
      "range": "starter"
    },
    {
      "modelType": "user",
      "name": "Gisele Draper",
      "stars": 100,
      "range": "starter"
    },
    {
      "modelType": "user",
      "name": "Octavio Oertel",
      "stars": 29,
      "range": "starter"
    },
    {
      "modelType": "user",
      "name": "Mirna Neubauer",
      "stars": 47,
      "range": "starter"
    },
    {
      "modelType": "user",
      "name": "Lea Myles",
      "stars": 18,
      "range": "starter"
    },
    {
      "modelType": "user",
      "name": "Milagros Nation",
      "stars": 64,
      "range": "starter"
    },
    {
      "modelType": "user",
      "name": "Emanuel Mcclaskey",
      "stars": 74,
      "range": "starter"
    },
    {
      "modelType": "user",
      "name": "Patrice Deen",
      "stars": 24,
      "range": "starter"
    },
    {
      "modelType": "user",
      "name": "Mozella Santana",
      "stars": 78,
      "range": "starter"
    },
    {
      "modelType": "user",
      "name": "Karin Pouncey",
      "stars": 21,
      "range": "starter"
    },
    {
      "modelType": "user",
      "name": "Krystin Melanson",
      "stars": 34,
      "range": "starter"
    },
    {
      "modelType": "user",
      "name": "Ashton Shoe",
      "stars": 23,
      "range": "starter"
    },
    {
      "modelType": "user",
      "name": "Hermila Alexandre",
      "stars": 17,
      "range": "starter"
    },
    {
      "modelType": "user",
      "name": "Concha Gelinas",
      "stars": 84,
      "range": "starter"
    },
    {
      "modelType": "user",
      "name": "Edythe Collyer",
      "stars": 93,
      "range": "starter"
    },
    {
      "modelType": "user",
      "name": "Lashawnda Nauman",
      "stars": 65,
      "range": "starter"
    },
    {
      "modelType": "user",
      "name": "Elidia Sideris",
      "stars": 75,
      "range": "starter"
    },
    {
      "modelType": "user",
      "name": "Mindy Kepner",
      "stars": 78,
      "range": "starter"
    },
    {
      "modelType": "user",
      "name": "Armandina Brady",
      "stars": 69,
      "range": "starter"
    },
    {
      "modelType": "user",
      "name": "Porfirio Pillow",
      "stars": 72,
      "range": "starter"
    },
    {
      "modelType": "user",
      "name": "Michiko Cantor",
      "stars": 2,
      "range": "starter"
    },
    {
      "modelType": "user",
      "name": "Fallon Totman",
      "stars": 11,
      "range": "starter"
    },
    {
      "modelType": "user",
      "name": "Janeth Bolan",
      "stars": 65,
      "range": "starter"
    },
    {
      "modelType": "user",
      "name": "Ozell Shiflett",
      "stars": 72,
      "range": "starter"
    }
  ]
}
